README.md
setup.py
melopero_apds9960/APDS_9960.py
melopero_apds9960/__init__.py
melopero_apds9960.egg-info/PKG-INFO
melopero_apds9960.egg-info/SOURCES.txt
melopero_apds9960.egg-info/dependency_links.txt
melopero_apds9960.egg-info/requires.txt
melopero_apds9960.egg-info/top_level.txt