Metadata-Version: 1.1
Name: melopero-apds9960
Version: 0.1.3
Summary: A module to easily access Melopero's APDS9960 sensor's features
Home-page: https://github.com/melopero/Melopero_APDS-9960
Author: Melopero
Author-email: info@melopero.com
License: MIT
Platform: UNKNOWN
Classifier: Development Status :: 3 - Alpha
Classifier: License :: OSI Approved :: MIT License
Classifier: Programming Language :: Python :: 3
Classifier: Programming Language :: Python :: 3.5
